federleicht/__init__.py
federleicht/args.py
federleicht/attrs.py
federleicht/cache.py
federleicht/config.py
federleicht/dataframe.py
federleicht/hash.py
federleicht-0.1.0.dist-info/LICENSE
federleicht-0.1.0.dist-info/METADATA
federleicht-0.1.0.dist-info/WHEEL
federleicht-0.1.0.dist-info/RECORD
