Metadata-Version: 2.1
Name: federleicht
Version: 0.1.0
Summary: lightweigth function decorators to cache your `pandas.DataFrame` as feather.
License: MIT
Keywords: cache,feather,pandas,pyarrow
Author: Christoph Dörrer
Author-email: d-chris@web.de
Requires-Python: >=3.9,<4.0
Classifier: License :: OSI Approved :: MIT License
Classifier: Operating System :: OS Independent
Classifier: Programming Language :: Python :: 3
Classifier: Programming Language :: Python :: 3.9
Classifier: Programming Language :: Python :: 3.10
Classifier: Programming Language :: Python :: 3.11
Classifier: Programming Language :: Python :: 3.12
Classifier: Programming Language :: Python :: 3.13
Provides-Extra: xxhash
Requires-Dist: pandas[feather] (>=2.0.0)
Requires-Dist: pathlibutil (>=0.3.0)
Requires-Dist: xxhash (>=3.5.0,<4.0.0) ; extra == "xxhash"
Project-URL: Documentation, https://d-chris.github.io/federleicht
Project-URL: Repository, https://github.com/d-chris/federleicht
